{
    "url": "http://127.0.0.1:8002/api/d2d/dd85bb99-f501-4338-ab56-8bb6f6c263b2/",
    "uuid": "dd85bb99-f501-4338-ab56-8bb6f6c263b2",
    "created_date": "2024-06-17T12:05:42.162206Z",
    "input_sources": [
        {
            "uuid": "d4813e4d-4bb9-4876-b115-efc3dc5f1760",
            "filename": "bwm-ng-debuginfo-0.6.3-3.fc40.x86_64.rpm",
            "download_url": "https://archive.fedoraproject.org/pub/fedora/linux/releases/40/Everything/x86_64/debug/tree/Packages/b/bwm-ng-debuginfo-0.6.3-3.fc40.x86_64.rpm#to",
            "is_uploaded": false,
            "tag": "to",
            "size": 55898,
            "is_file": true,
            "exists": true
        },
        {
            "uuid": "990cff3c-561d-4998-be85-c9585e9a83e2",
            "filename": "bwm-ng-debugsource-0.6.3-3.fc40.x86_64.rpm",
            "download_url": "https://archive.fedoraproject.org/pub/fedora/linux/releases/40/Everything/x86_64/debug/tree/Packages/b/bwm-ng-debugsource-0.6.3-3.fc40.x86_64.rpm#from",
            "is_uploaded": false,
            "tag": "from",
            "size": 35861,
            "is_file": true,
            "exists": true
        }
    ],
    "runs": [
        "a5e2cbef-0ba5-4ae4-867c-500b18f58b78"
    ],
    "resource_count": 38,
    "package_count": 1,
    "dependency_count": 0,
    "relation_count": 26,
    "codebase_resources_summary": {
        "ignored-directory": 15,
        "requires-review": 1,
        "scanned": 22
    },
    "discovered_packages_summary": {
        "total": 1,
        "with_missing_resources": 0,
        "with_modified_resources": 0
    },
    "discovered_dependencies_summary": {
        "total": 0,
        "is_runtime": 0,
        "is_optional": 0,
        "is_resolved": 0
    },
    "codebase_relations_summary": {
        "dwarf_compiled_paths": 4,
        "dwarf_included_paths": 22
    },
    "codebase_resources_discrepancies": {
        "total": 1
    }
}