{
    "headers": [
        {
            "tool_name": "scanpipe",
            "tool_version": "v5.0.0-40-g124e022",
            "other_tools": [
                "pkg:pypi/scancode-toolkit@32.1.0"
            ],
            "notice": "Generated with ScanCode.io and provided on an \"AS IS\" BASIS, WITHOUT WARRANTIES\nOR CONDITIONS OF ANY KIND, either express or implied.\nNo content created from ScanCode.io should be considered or used as legal advice.\nConsult an Attorney for any legal advice.\nScanCode.io is a free software code scanning tool from nexB Inc. and others\nlicensed under the Apache License version 2.0.\nScanCode is a trademark of nexB Inc.\nVisit https://github.com/nexB/scancode.io for support and download.\n",
            "uuid": "1216970d-cd28-4b40-bc06-ce8b166ae17a",
            "created_date": "2024-06-17T11:00:08.071Z",
            "notes": "",
            "settings": {},
            "input_sources": [
                {
                    "uuid": "59bb45d1-438e-440e-b764-70f2a924c6e6",
                    "filename": "",
                    "download_url": "https://archive.fedoraproject.org/pub/fedora/linux/releases/40/Everything/x86_64/debug/tree/Packages/b/bacula-debugsource-13.0.4-4.fc40.x86_64.rpm#from",
                    "is_uploaded": false,
                    "tag": "from",
                    "size": null,
                    "is_file": true,
                    "exists": false
                },
                {
                    "uuid": "18fa3ac7-4645-4196-aefd-1abf35f9e469",
                    "filename": "bacula-debuginfo-13.0.4-4.fc40.x86_64.rpm",
                    "download_url": "https://archive.fedoraproject.org/pub/fedora/linux/releases/40/Everything/x86_64/debug/tree/Packages/b/bacula-debuginfo-13.0.4-4.fc40.x86_64.rpm#to",
                    "is_uploaded": false,
                    "tag": "to",
                    "size": 355361,
                    "is_file": true,
                    "exists": true
                }
            ],
            "runs": [
                {
                    "pipeline_name": "d2d",
                    "status": "failure",
                    "description": "Establish relationships between two code trees: deployment and development.",
                    "uuid": "0a3cc845-0306-47c8-9f44-b534cc8c5c05",
                    "created_date": "2024-06-17T11:00:08.078853Z",
                    "scancodeio_version": "v5.0.0-40-g124e022",
                    "task_id": "0a3cc845-0306-47c8-9f44-b534cc8c5c05",
                    "task_start_date": "2024-06-17T11:00:08.103940Z",
                    "task_end_date": "2024-06-17T11:00:23.958648Z",
                    "task_exitcode": 1,
                    "task_output": "[ConnectionError(ReadTimeoutError(\"HTTPSConnectionPool(host='archive.fedoraproject.org', port=443): Read timed out.\"))]\n\nTraceback:\n  File \"/home/tg1999/Desktop/purldb/venv/lib/python3.10/site-packages/scanpipe/pipelines/__init__.py\", line 204, in execute\n    step(self)\n  File \"/home/tg1999/Desktop/purldb/venv/lib/python3.10/site-packages/scanpipe/pipelines/__init__.py\", line 243, in download_missing_inputs\n    raise InputFileError(errors)\n",
                    "log": "2024-06-17 11:00:08.10 Pipeline [d2d] starting\n2024-06-17 11:00:08.11 Step [download_missing_inputs] starting\n2024-06-17 11:00:08.11 Fetching input from https://archive.fedoraproject.org/pub/fedora/linux/releases/40/Everything/x86_64/debug/tree/Packages/b/bacula-debugsource-13.0.4-4.fc40.x86_64.rpm#from\n2024-06-17 11:00:21.15 https://archive.fedoraproject.org/pub/fedora/linux/releases/40/Everything/x86_64/debug/tree/Packages/b/bacula-debugsource-13.0.4-4.fc40.x86_64.rpm#from could not be fetched.\n2024-06-17 11:00:21.16 Fetching input from https://archive.fedoraproject.org/pub/fedora/linux/releases/40/Everything/x86_64/debug/tree/Packages/b/bacula-debuginfo-13.0.4-4.fc40.x86_64.rpm#to\n2024-06-17 11:00:23.95 Pipeline failed\n",
                    "execution_time": 15
                }
            ],
            "extra_data": {}
        }
    ],
    "packages": [],
    "dependencies": [],
    "files": [],
    "relations": []
}