{
    "url": "http://127.0.0.1:8002/api/d2d/e7b384d0-36d8-4727-9670-d44663c1c76d/",
    "uuid": "e7b384d0-36d8-4727-9670-d44663c1c76d",
    "created_date": "2024-06-13T10:22:08.357476Z",
    "input_sources": [
        {
            "uuid": "b595ed16-b247-4039-a81d-17beaee793ce",
            "filename": "aalib-debuginfo-1.4.0-0.50.rc5.fc40.x86_64.rpm",
            "download_url": "https://archive.fedoraproject.org/pub/fedora/linux/releases/40/Everything/x86_64/debug/tree/Packages/a/aalib-debuginfo-1.4.0-0.50.rc5.fc40.x86_64.rpm#to",
            "is_uploaded": false,
            "tag": "to",
            "size": 27719,
            "is_file": true,
            "exists": true
        },
        {
            "uuid": "416764b0-6d37-4137-9778-72d0631b5ffc",
            "filename": "aalib-debugsource-1.4.0-0.50.rc5.fc40.x86_64.rpm",
            "download_url": "https://archive.fedoraproject.org/pub/fedora/linux/releases/40/Everything/x86_64/debug/tree/Packages/a/aalib-debugsource-1.4.0-0.50.rc5.fc40.x86_64.rpm#from",
            "is_uploaded": false,
            "tag": "from",
            "size": 82957,
            "is_file": true,
            "exists": true
        }
    ],
    "runs": [
        "5c6636c7-2847-4b1d-a21b-a930183759af"
    ],
    "resource_count": 86,
    "package_count": 1,
    "dependency_count": 0,
    "relation_count": 10,
    "codebase_resources_summary": {
        "ignored-directory": 18,
        "no-licenses": 5,
        "not-deployed": 57,
        "requires-review": 5,
        "scanned": 1
    },
    "discovered_packages_summary": {
        "total": 1,
        "with_missing_resources": 0,
        "with_modified_resources": 0
    },
    "discovered_dependencies_summary": {
        "total": 0,
        "is_runtime": 0,
        "is_optional": 0,
        "is_resolved": 0
    },
    "codebase_relations_summary": {
        "dwarf_included_paths": 10
    },
    "codebase_resources_discrepancies": {
        "total": 5
    }
}