{
    "resources_with_discrepancy": [
        {
            "dwarf_compiled_paths_not_mapped_count": 2, 
            "path": "to/usr/lib/debug/usr/lib64/libbio2jack.so.0.9.0-0.9-33.fc40.x86_64.debug", 
            "dwarf_included_paths_not_mapped_count": 24
        }
    ], 
    "input_sources": [
        {
            "is_uploaded": false, 
            "uuid": "839fcea4-fc27-4c94-8f7a-eca34a5d29fc", 
            "exists": true, 
            "download_url": "https://archive.fedoraproject.org/pub/fedora/linux/releases/40/Everything/x86_64/debug/tree/Packages/b/bio2jack-debuginfo-0.9-33.fc40.x86_64.rpm#to", 
            "filename": "bio2jack-debuginfo-0.9-33.fc40.x86_64.rpm", 
            "tag": "to", 
            "is_file": true, 
            "size": 40971
        }, 
        {
            "is_uploaded": false, 
            "uuid": "91961066-a703-4f20-b92b-b16c320c927d", 
            "exists": true, 
            "download_url": "https://archive.fedoraproject.org/pub/fedora/linux/releases/40/Everything/x86_64/debug/tree/Packages/b/bio2jack-debugsource-0.9-33.fc40.x86_64.rpm#from", 
            "filename": "bio2jack-debugsource-0.9-33.fc40.x86_64.rpm", 
            "tag": "from", 
            "is_file": true, 
            "size": 26026
        }
    ], 
    "uuid": "c9ff9497-cc36-4980-b91c-4797656327fe", 
    "resource_count": 16, 
    "url": "http://127.0.0.1:8002/api/d2d/c9ff9497-cc36-4980-b91c-4797656327fe/", 
    "package_count": 1, 
    "runs": [
        "51b0768d-d7c1-4ab3-a79c-c620255cefd3"
    ], 
    "discovered_dependencies_summary": {
        "is_runtime": 0, 
        "is_optional": 0, 
        "total": 0, 
        "is_resolved": 0
    }, 
    "codebase_resources_summary": {
        "ignored-directory": 13, 
        "scanned": 2, 
        "requires-review": 1
    }, 
    "codebase_resources_discrepancies": {
        "total": 1
    }, 
    "relation_count": 2, 
    "created_date": "2024-06-17T12:06:40.354816Z", 
    "dependency_count": 0, 
    "discovered_packages_summary": {
        "with_missing_resources": 0, 
        "total": 1, 
        "with_modified_resources": 0
    }, 
    "codebase_relations_summary": {
        "dwarf_included_paths": 2
    }
}