{
    "resources_with_discrepancy": [
        {
            "dwarf_compiled_paths_not_mapped_count": 2, 
            "path": "to/usr/lib/debug/usr/bin/archivemount-0.9.1-10.fc40.x86_64.debug", 
            "dwarf_included_paths_not_mapped_count": 44
        }
    ], 
    "input_sources": [
        {
            "is_uploaded": false, 
            "uuid": "ee8b801d-fc65-4f26-bbbb-cb5292ce8a41", 
            "exists": true, 
            "download_url": "https://archive.fedoraproject.org/pub/fedora/linux/releases/40/Everything/x86_64/debug/tree/Packages/a/archivemount-debuginfo-0.9.1-10.fc40.x86_64.rpm#to", 
            "filename": "archivemount-debuginfo-0.9.1-10.fc40.x86_64.rpm", 
            "tag": "to", 
            "is_file": true, 
            "size": 72287
        }, 
        {
            "is_uploaded": false, 
            "uuid": "7831a127-a203-453a-84af-ee5a38e14d79", 
            "exists": true, 
            "download_url": "https://archive.fedoraproject.org/pub/fedora/linux/releases/40/Everything/x86_64/debug/tree/Packages/a/archivemount-debugsource-0.9.1-10.fc40.x86_64.rpm#from", 
            "filename": "archivemount-debugsource-0.9.1-10.fc40.x86_64.rpm", 
            "tag": "from", 
            "is_file": true, 
            "size": 32621
        }
    ], 
    "uuid": "f41255f4-596a-41ff-a947-b5732f8f0d39", 
    "resource_count": 16, 
    "url": "http://127.0.0.1:8002/api/d2d/f41255f4-596a-41ff-a947-b5732f8f0d39/", 
    "package_count": 2, 
    "runs": [
        "ca14c3bb-47a8-428d-84a7-e2acb0d34c33"
    ], 
    "discovered_dependencies_summary": {
        "is_runtime": 0, 
        "is_optional": 0, 
        "total": 0, 
        "is_resolved": 0
    }, 
    "codebase_resources_summary": {
        "ignored-directory": 13, 
        "scanned": 2, 
        "requires-review": 1
    }, 
    "codebase_resources_discrepancies": {
        "total": 1
    }, 
    "relation_count": 2, 
    "created_date": "2024-06-13T11:30:38.824833Z", 
    "dependency_count": 0, 
    "discovered_packages_summary": {
        "with_missing_resources": 0, 
        "total": 2, 
        "with_modified_resources": 0
    }, 
    "codebase_relations_summary": {
        "dwarf_included_paths": 2
    }
}