{
    "resources_with_discrepancy": [
        {
            "dwarf_compiled_paths_not_mapped_count": 0, 
            "path": "to/usr/lib/debug/.dwz/atf-0.21-4.fc40.x86_64", 
            "dwarf_included_paths_not_mapped_count": 109
        }
    ], 
    "input_sources": [
        {
            "is_uploaded": false, 
            "uuid": "dc595432-fd01-4d71-b5d8-f2df564a4a46", 
            "exists": true, 
            "download_url": "https://archive.fedoraproject.org/pub/fedora/linux/releases/40/Everything/x86_64/debug/tree/Packages/a/atf-debuginfo-0.21-4.fc40.x86_64.rpm#to", 
            "filename": "atf-debuginfo-0.21-4.fc40.x86_64.rpm", 
            "tag": "to", 
            "is_file": true, 
            "size": 82699
        }, 
        {
            "is_uploaded": false, 
            "uuid": "1ea4e5ad-38f5-4b7e-9232-91ea9236a7af", 
            "exists": true, 
            "download_url": "https://archive.fedoraproject.org/pub/fedora/linux/releases/40/Everything/x86_64/debug/tree/Packages/a/atf-debugsource-0.21-4.fc40.x86_64.rpm#from", 
            "filename": "atf-debugsource-0.21-4.fc40.x86_64.rpm", 
            "tag": "from", 
            "is_file": true, 
            "size": 121772
        }
    ], 
    "uuid": "15e5922e-37a2-493f-be0d-5ff251999a74", 
    "resource_count": 111, 
    "url": "http://127.0.0.1:8002/api/d2d/15e5922e-37a2-493f-be0d-5ff251999a74/", 
    "package_count": 1, 
    "runs": [
        "9db26fa8-898d-4b59-b793-9febee90d743"
    ], 
    "discovered_dependencies_summary": {
        "is_runtime": 0, 
        "is_optional": 0, 
        "total": 0, 
        "is_resolved": 0
    }, 
    "codebase_resources_summary": {
        "ignored-directory": 16, 
        "scanned": 24, 
        "requires-review": 1, 
        "not-deployed": 70
    }, 
    "codebase_resources_discrepancies": {
        "total": 1
    }, 
    "relation_count": 24, 
    "created_date": "2024-06-13T21:35:56.366957Z", 
    "dependency_count": 0, 
    "discovered_packages_summary": {
        "with_missing_resources": 0, 
        "total": 1, 
        "with_modified_resources": 0
    }, 
    "codebase_relations_summary": {
        "dwarf_included_paths": 24
    }
}